pipeworks/__init__.py
pipeworks-0.0.3.dist-info/LICENSE
pipeworks-0.0.3.dist-info/METADATA
pipeworks-0.0.3.dist-info/WHEEL
pipeworks-0.0.3.dist-info/top_level.txt
pipeworks-0.0.3.dist-info/RECORD
