Metadata-Version: 2.1
Name: pipeworks
Version: 0.0.3
Summary: Collection of classes for calculating pressurized and open channel flow hydraulics for outlet works. 
Author-email: Kevin Kuei <kevinkuei@gmail.com>
Project-URL: Homepage, https://github.com/kckuei/pipeworks
Project-URL: Bug Tracker, https://github.com/kckuei/pipeworks/issues
Classifier: Programming Language :: Python :: 3
Classifier: License :: OSI Approved :: MIT License
Classifier: Operating System :: OS Independent
Requires-Python: >=3.9.7
License-File: LICENSE
